[
    {
        "order_id": "#SP7804",
        "username": "alrafi",
        "cart": [
            {
                "product_id": 1,
                "name": "BURGET",
                "price": 11.0,
                "quantity": 1,
                "extras": []
            },
            {
                "product_id": 5,
                "name": "Pizza",
                "price": 100.0,
                "quantity": 1,
                "extras": []
            }
        ],
        "base_total": 111.0,
        "extras_total": 0,
        "vat": 16.65,
        "tax": 5.550000000000001,
        "total_price": 133.20000000000002,
        "payment_method": "Credit Card",
        "status": "Pending"
    },
    {
        "order_id": "#SP4548",
        "username": "alrafi",
        "cart": [
            {
                "product_id": 3,
                "name": "asd",
                "price": 23,
                "quantity": 5,
                "extras": []
            }
        ],
        "base_total": 115,
        "extras_total": 0,
        "vat": 17.25,
        "tax": 5.75,
        "total_price": 138.0,
        "payment_method": "Credit Card",
        "status": "Pending"
    }
]